LICENSE.txt
MANIFEST.in
README.txt
ez_setup.py
setup.py
all_spark_cube_client/__init__.py
all_spark_cube_client.egg-info/PKG-INFO
all_spark_cube_client.egg-info/SOURCES.txt
all_spark_cube_client.egg-info/dependency_links.txt
all_spark_cube_client.egg-info/requires.txt
all_spark_cube_client.egg-info/top_level.txt
cube_interface/CubeInterface.py
cube_interface/__init__.py
cube_interface/constants.py
cube_interface/ttypes.py