Metadata-Version: 1.1
Name: all-spark-cube-client
Version: 0.5
Summary: Python client library for the All Spark Cube
Home-page: https://github.com/chadharrington/all_spark_cube
Author: Chad Harrington
Author-email: chad.harrington@gmail.com
License: MIT
Platform: UNKNOWN
Classifier: Development Status :: 4 - Beta
Classifier: License :: OSI Approved :: MIT License
Classifier: Programming Language :: Python :: 2.7
Classifier: Intended Audience :: Developers
Classifier: Topic :: System :: Distributed Computing
